Metadata-Version: 1.1
Name: video-frame-processor
Version: 0.0.1
Summary: Python 3 library to make video frame processing easier.
Home-page: https://github.com/waikato-datamining/video-frame-processor
Author: Peter Reutemann
Author-email: fracpete@waikato.ac.nz
License: MIT License
Platform: UNKNOWN
Classifier: Development Status :: 4 - Beta
Classifier: License :: OSI Approved :: MIT License
Classifier: Topic :: Multimedia :: Video
Classifier: Programming Language :: Python :: 3
